matplotlib_aximgcache/__init__.py
matplotlib_aximgcache/imgcache.py
matplotlib_aximgcache-0.1.0.dist-info/METADATA
matplotlib_aximgcache-0.1.0.dist-info/WHEEL
matplotlib_aximgcache-0.1.0.dist-info/top_level.txt
matplotlib_aximgcache-0.1.0.dist-info/RECORD
