Metadata-Version: 2.1
Name: matplotlib-aximgcache
Version: 0.1.0
Summary: Easily store and re-replot matplotlib Axes content
Home-page: https://github.com/leifdenby/matplotlib-aximgcache
Author: Leif Denby
Author-email: leif@denby.eu
Requires-Dist: matplotlib
Requires-Dist: Pillow
Provides-Extra: dev
Requires-Dist: pytest ; extra == 'dev'
Requires-Dist: nbval ; extra == 'dev'
Requires-Dist: nb-black ; extra == 'dev'
Requires-Dist: pre-commit ; extra == 'dev'
Requires-Dist: ipython ; extra == 'dev'
Provides-Extra: test
Requires-Dist: pytest ; extra == 'test'
Requires-Dist: nbval ; extra == 'test'
Requires-Dist: nb-black ; extra == 'test'
